currency/__init__.py
currency/currency.csv
currency/functions.py
currency/main.py
currency_ch-0.1.0.dist-info/LICENSE
currency_ch-0.1.0.dist-info/METADATA
currency_ch-0.1.0.dist-info/WHEEL
currency_ch-0.1.0.dist-info/top_level.txt
currency_ch-0.1.0.dist-info/RECORD
