Metadata-Version: 2.1
Name: currency-ch
Version: 0.1.0
Summary: Python library for currency exchange.
Home-page: https://github.com/calebyhan/currency
Author: Caleb Han
Author-email: calebhantech@gmail.com
License: MIT
Classifier: License :: OSI Approved :: MIT License
Classifier: Programming Language :: Python :: 3
Classifier: Operating System :: OS Independent
License-File: LICENSE
